paperspace/__init__.py
paperspace/config.py
paperspace/jobs.py
paperspace/login.py
paperspace/machines.py
paperspace/main.py
paperspace/method.py
paperspace/networks.py
paperspace/scripts.py
paperspace/templates.py
paperspace/users.py
paperspace-0.0.15.dist-info/LICENSE.txt
paperspace-0.0.15.dist-info/METADATA
paperspace-0.0.15.dist-info/WHEEL
paperspace-0.0.15.dist-info/entry_points.txt
paperspace-0.0.15.dist-info/top_level.txt
paperspace-0.0.15.dist-info/RECORD
