Metadata-Version: 2.1
Name: paperspace
Version: 0.0.15
Summary: Paperspace Python
Home-page: https://github.com/paperspace/paperspace-python
Author: Paperspace Co.
Author-email: info@paperspace.com
License: UNKNOWN
Keywords: paperspace api development library
Platform: UNKNOWN
Classifier: Development Status :: 3 - Alpha
Classifier: Intended Audience :: Developers
Classifier: Topic :: Software Development :: Libraries
Classifier: License :: OSI Approved :: ISC License (ISCL)
Classifier: Programming Language :: Python :: 2.7
Classifier: Programming Language :: Python :: 3.4
Classifier: Programming Language :: Python :: 3.5
Classifier: Programming Language :: Python :: 3.6
Requires-Dist: requests[security]
Requires-Dist: boto3
Requires-Dist: botocore
Requires-Dist: six
